setup.py
ifsugar/__init__.py
ifsugar/ifsugar.py
ifsugar.egg-info/PKG-INFO
ifsugar.egg-info/SOURCES.txt
ifsugar.egg-info/dependency_links.txt
ifsugar.egg-info/top_level.txt