Metadata-Version: 1.0
Name: ifsugar
Version: 0.1.3
Summary: syntax sugars for easyer understood coding: _if, _try, _times
Home-page: https://github.com/qorzj/ifsugar
Author: qorzj
Author-email: inull@qq.com
License: Public domain
Keywords: ifsugar syntax sugar times try if
Platform: any
